Workbook

Sheet Produtos
A1: BAUMEVIE | Cadastro de Produtos e Estoque
A3: Produto | B3: Categoria | C3: Estoque Inicial | D3: Entradas | E3: Vendas | F3: AMOSTRA | G3: Estoque Atual | H3: Preço de Venda (R$) | I3: Custo Unitário (R$) | J3: Margem Unitária (R$) | K3: Valor em Estoque varejo(R$) | L3: Estoque Mínimo | M3: Status
A4: DIFUSOR NARDO | B4: Difusor | C4: 174 | D4: =SUMIFS('Vendas diárias'!$D:$D,'Vendas diárias'!$B:$B,$A4,'Vendas diárias'!$C:$C,"Entrada") -> 0 | E4: 3 | F4: 0 | G4: =SUM(C4+D4-E4-F4) -> 171 | H4: 159.9 | I4: 63.64 | J4: =H4-I4 -> 96.26 | K4: =SUM(G4*H4) -> 27342.9 | L4: 5 | M4: =IF(G4<=L4,"REPOR","OK") -> OK
A5: DIFUSOR ACACIA | B5: Difusor | C5: 98 | D5: =SUMIFS('Vendas diárias'!$D:$D,'Vendas diárias'!$B:$B,$A5,'Vendas diárias'!$C:$C,"Entrada") -> 0 | E5: =SUMIFS('Vendas diárias'!$D:$D,'Vendas diárias'!$B:$B,$A5,'Vendas diárias'!$C:$C,"Venda") -> 1 | G5: =SUM(C5+D5-E5-F5) -> 97 | H5: 159.9 | I5: 63.64 | J5: =H5-I5 -> 96.26 | K5: =SUM(H5*G5) -> 15510.3 | L5: 6 | M5: =IF(G5<=L5,"REPOR","OK") -> OK
A6: SABONETE NARDO | B6: Sabonete Líquido | C6: 168 | D6: =SUMIFS('Vendas diárias'!$D:$D,'Vendas diárias'!$B:$B,$A6,'Vendas diárias'!$C:$C,"Entrada") -> 0 | E6: 3 | G6: =SUM(C6+D6-E6-F6) -> 165 | H6: 129.9 | I6: 47.73 | J6: =H6-I6 -> 82.17 | K6: =SUM(G6*H6) -> 21433.5 | L6: 8 | M6: =IF(G6<=L6,"REPOR","OK") -> OK
A7: SABONETE ACÁCIA | B7: Sabonete Líquido | C7: 187 | D7: =SUMIFS('Vendas diárias'!$D:$D,'Vendas diárias'!$B:$B,$A7,'Vendas diárias'!$C:$C,"Entrada") -> 0 | E7: =SUMIFS('Vendas diárias'!$D:$D,'Vendas diárias'!$B:$B,$A7,'Vendas diárias'!$C:$C,"Venda") -> 0 | G7: =SUM(C7+D7-E7-F7) -> 187 | H7: 129.9 | I7: 47.73 | J7: =H7-I7 -> 82.17 | K7: =SUM(H7*G7) -> 24291.3 | L7: 5 | M7: =IF(G7<=L7,"REPOR","OK") -> OK
A8: HOME SPRAY AMENDOA | B8: Home Spray | C8: 38 | D8: =SUMIFS('Vendas diárias'!$D:$D,'Vendas diárias'!$B:$B,$A8,'Vendas diárias'!$C:$C,"Entrada") -> 0 | E8: 4 | F8: 1 | G8: =SUM(C8+D8-E8-F8) -> 33 | H8: 55.5 | I8: 21.99 | J8: =H8-I8 -> 33.51 | K8: =SUM(G8*H8) -> 1831.5 | L8: 5 | M8: =IF(G8<=L8,"REPOR","OK") -> OK
A9: HOME SPRAY SANDALO | B9: Home Spray | C9: 21 | D9: =SUMIFS('Vendas diárias'!$D:$D,'Vendas diárias'!$B:$B,$A9,'Vendas diárias'!$C:$C,"Entrada") -> 0 | E9: 4 | F9: 1 | G9: =SUM(C9+D9-E9-F9) -> 16 | H9: 55.5 | I9: 21.99 | J9: =H9-I9 -> 33.51 | K9: =SUM(H9*G9) -> 888 | L9: 5 | M9: =IF(G9<=L9,"REPOR","OK") -> OK
A10: BODY SPLASH FIGO | B10: Body Splash | C10: 58 | D10: =SUMIFS('Vendas diárias'!$D:$D,'Vendas diárias'!$B:$B,$A10,'Vendas diárias'!$C:$C,"Entrada") -> 0 | E10: 8 | F10: 1 | G10: =SUM(C10+D10-E10-F10) -> 49 | H10: 79 | I10: 28.68 | J10: =H10-I10 -> 50.32 | K10: =SUM(G10*H10) -> 3871 | L10: 6 | M10: =IF(G10<=L10,"REPOR","OK") -> OK
A11: BODY SPLASH ROMÃ | B11: Body Splash | C11: 56 | D11: =SUMIFS('Vendas diárias'!$D:$D,'Vendas diárias'!$B:$B,$A11,'Vendas diárias'!$C:$C,"Entrada") -> 0 | E11: 10 | F11: 1 | G11: =SUM(C11+D11-E11-F11) -> 45 | H11: 79 | I11: 28.68 | J11: =H11-I11 -> 50.32 | K11: =SUM(H11*G11) -> 3555 | L11: 6 | M11: =IF(G11<=L11,"REPOR","OK") -> OK
A12: REFIL SABONETE NARDO | B12: Sabonete Líquido | C12: 3 | D12: =SUMIFS('Vendas diárias'!$D:$D,'Vendas diárias'!$B:$B,$A12,'Vendas diárias'!$C:$C,"Entrada") -> 0 | E12: =SUMIFS('Vendas diárias'!$D:$D,'Vendas diárias'!$B:$B,$A12,'Vendas diárias'!$C:$C,"Venda") -> 0 | F12: 1 | G12: =SUM(C12+D12-E12-F12) -> 2 | H12: 46 | I12: 33.88 | J12: =H12-I12 -> 12.12 | K12: =SUM(G12*H12) -> 92 | L12: 6 | M12: =IF(G12<=L12,"REPOR","OK") -> REPOR
A13: REFIL SABONETE ACÁCIA | B13: Sabonete Líquido | C13: 2 | D13: =SUMIFS('Vendas diárias'!$D:$D,'Vendas diárias'!$B:$B,$A13,'Vendas diárias'!$C:$C,"Entrada") -> 0 | E13: =SUMIFS('Vendas diárias'!$D:$D,'Vendas diárias'!$B:$B,$A13,'Vendas diárias'!$C:$C,"Venda") -> 0 | G13: =SUM(C13+D13-E13-F13) -> 2 | H13: 46 | I13: 33.88 | J13: =H13-I13 -> 12.12 | K13: =SUM(H13*G13) -> 92 | L13: 5 | M13: =IF(G13<=L13,"REPOR","OK") -> REPOR
A14: REFIL DIFUSOR NARDO | B14: Difusor | C14: 10 | D14: 0 | E14: 2 | G14: =SUM(C14+D14-E14-F14) -> 8 | H14: 86 | I14: 23.55 | J14: =H14-I14 -> 62.45 | K14: =SUM(G14*H14) -> 688 | L14: 6 | M14: =IF(G14<=L14,"REPOR","OK") -> OK
A15: REFIL DIFUSOR ACÁCIA | B15: Difusor | C15: 3 | D15: 0 | E15: 2 | F15: 1 | G15: =SUM(C15+D15-E15-F15) -> 0 | H15: 86 | I15: 23.55 | J15: =H15-I15 -> 62.45 | K15: =SUM(H15*G15) -> 0 | L15: 5 | M15: =IF(G15<=L15,"REPOR","OK") -> REPOR
A16: TOTAL | C16: =SUM(C4:C15) -> 818 | D16: =SUM(D4:D13) -> 0 | E16: =SUM(E4:E15) -> 37 | G16: =SUM(G4:G15) -> 775 | K16: =SUM(K4:K15) -> 99595.5

Sheet Vendas diárias
A1: BAUMEVIE | Vendas Diárias
A3: Data | B3: Produto | C3: Tipo | D3: Quantidade | E3: Preço Unitário (R$) | F3: Valor Total (R$) | G3: Custo Total (R$) | H3: Lucro Bruto (R$) | I3: Canal de Venda | J3: Observações | L3: Resumo
A4: 16/03/2026 | B4: DIFUSOR NARDO | C4: Venda | D4: 0 | E4: 159.9 | F4: 0 | G4: =IF(OR(B4="",D4=""),"",IFERROR(D4*VLOOKUP(B4,Produtos!$A$4:$I$13,9,FALSE),"")) -> 0 | H4: =IF(C4="Venda",IF(OR(F4="",G4=""),"",F4-G4),"") -> 0 | I4: Loja | L4: Vendas totais | M4: =SUMIFS(F:F,C:C,"Venda") -> 2052.7
A5: 16/03/2026 | B5: DIFUSOR ACACIA | C5: Venda | D5: 1 | E5: 159.9 | F5: 140 | G5: =IF(OR(B5="",D5=""),"",IFERROR(D5*VLOOKUP(B5,Produtos!$A$4:$I$13,9,FALSE),"")) -> 63.64 | H5: =IF(C5="Venda",IF(OR(F5="",G5=""),"",F5-G5),"") -> 76.36 | I5: Loja | L5: Lucro bruto | M5: =SUM(H:H) -> 993.99
A6: 16/03/2026 | B6: SABONETE NARDO | C6: Venda | D6: 0 | E6: 129.9 | F6: =IF(OR(D6="",E6=""),"",D6*E6) -> 0 | G6: =IF(OR(B6="",D6=""),"",IFERROR(D6*VLOOKUP(B6,Produtos!$A$4:$I$13,9,FALSE),"")) -> 0 | H6: =IF(C6="Venda",IF(OR(F6="",G6=""),"",F6-G6),"") -> 0 | I6: Loja | L6: Itens vendidos | M6: =SUMIFS(D:D,C:C,"Venda") -> 24
A7: 16/03/2026 | B7: SABONETE ACÁCIA | C7: Venda | D7: 0 | E7: 129.9 | F7: =IF(OR(D7="",E7=""),"",D7*E7) -> 0 | G7: =IF(OR(B7="",D7=""),"",IFERROR(D7*VLOOKUP(B7,Produtos!$A$4:$I$13,9,FALSE),"")) -> 0 | H7: =IF(C7="Venda",IF(OR(F7="",G7=""),"",F7-G7),"") -> 0 | I7: Loja | L7: Entradas | M7: =SUMIFS(D:D,C:C,"Entrada") -> 0
A8: 16/03/2026 | B8: HOME SPRAY AMENDOA | C8: Venda | D8: 1 | E8: 55.5 | F8: 50 | G8: =IF(OR(B8="",D8=""),"",IFERROR(D8*VLOOKUP(B8,Produtos!$A$4:$I$13,9,FALSE),"")) -> 21.99 | H8: =IF(C8="Venda",IF(OR(F8="",G8=""),"",F8-G8),"") -> 28.01 | I8: Loja
A9: 16/03/2026 | B9: HOME SPRAY SANDALO | C9: Venda | D9: 1 | E9: 55.5 | F9: 50 | G9: =IF(OR(B9="",D9=""),"",IFERROR(D9*VLOOKUP(B9,Produtos!$A$4:$I$13,9,FALSE),"")) -> 21.99 | H9: =IF(C9="Venda",IF(OR(F9="",G9=""),"",F9-G9),"") -> 28.01 | I9: Loja
A10: 16/03/2026 | B10: BODY SPLASH FIGO | C10: Venda | D10: 0 | E10: 79 | F10: =IF(OR(D10="",E10=""),"",D10*E10) -> 0 | G10: =IF(OR(B10="",D10=""),"",IFERROR(D10*VLOOKUP(B10,Produtos!$A$4:$I$13,9,FALSE),"")) -> 0 | H10: =IF(C10="Venda",IF(OR(F10="",G10=""),"",F10-G10),"") -> 0 | I10: Loja
A11: 16/03/2026 | B11: BODY SPLASH ROMÃ | C11: Venda | D11: 0 | E11: 79 | F11: =IF(OR(D11="",E11=""),"",D11*E11) -> 0 | G11: =IF(OR(B11="",D11=""),"",IFERROR(D11*VLOOKUP(B11,Produtos!$A$4:$I$13,9,FALSE),"")) -> 0 | H11: =IF(C11="Venda",IF(OR(F11="",G11=""),"",F11-G11),"") -> 0 | I11: Loja
A12: 16/03/2026 | B12: REFIL SABONETE NARDO | C12: Venda | D12: 0 | E12: 46 | F12: =IF(OR(D12="",E12=""),"",D12*E12) -> 0 | G12: =IF(OR(B12="",D12=""),"",IFERROR(D12*VLOOKUP(B12,Produtos!$A$4:$I$13,9,FALSE),"")) -> 0 | H12: =IF(C12="Venda",IF(OR(F12="",G12=""),"",F12-G12),"") -> 0 | I12: Loja
A13: 16/03/2026 | B13: REFIL SABONETE ACÁCIA | C13: Venda | D13: 0 | E13: 46 | F13: =IF(OR(D13="",E13=""),"",D13*E13) -> 0 | G13: =IF(OR(B13="",D13=""),"",IFERROR(D13*VLOOKUP(B13,Produtos!$A$4:$I$13,9,FALSE),"")) -> 0 | H13: =IF(C13="Venda",IF(OR(F13="",G13=""),"",F13-G13),"") -> 0 | I13: Loja
A14: 16/03/2026 | B14: REFIL DIFUSOR NARDO | C14: Venda | D14: 0 | E14: 86 | F14: =IF(OR(D14="",E14=""),"",D14*E14) -> 0 | G14: =IF(OR(B14="",D14=""),"",IFERROR(D14*VLOOKUP(B14,Produtos!$A$4:$I$13,9,FALSE),"")) | H14: =IF(C14="Venda",IF(OR(F14="",G14=""),"",F14-G14),"") | I14: Loja
A15: 16/03/2026 | B15: REFIL DIFUSOR ACÁCIA | C15: Venda | D15: 1 | E15: 86 | F15: =IF(OR(D15="",E15=""),"",D15*E15) -> 86 | G15: =IF(OR(B15="",D15=""),"",IFERROR(D15*VLOOKUP(B15,Produtos!$A$4:$I$13,9,FALSE),"")) | H15: =IF(C15="Venda",IF(OR(F15="",G15=""),"",F15-G15),"") | I15: Loja
E16: =IF(B16="","",IFERROR(VLOOKUP(B16,Produtos!$A$4:$I$13,8,FALSE),"")) | F16: =SUM(F5:F15) -> 326 | G16: =IF(OR(B16="",D16=""),"",IFERROR(D16*VLOOKUP(B16,Produtos!$A$4:$I$13,9,FALSE),"")) | H16: =IF(C16="Venda",IF(OR(F16="",G16=""),"",F16-G16),"")
E17: =IF(B17="","",IFERROR(VLOOKUP(B17,Produtos!$A$4:$I$13,8,FALSE),"")) | F17: =IF(OR(D17="",E17=""),"",D17*E17) | G17: =IF(OR(B17="",D17=""),"",IFERROR(D17*VLOOKUP(B17,Produtos!$A$4:$I$13,9,FALSE),"")) | H17: =IF(C17="Venda",IF(OR(F17="",G17=""),"",F17-G17),"")
A18: Data | B18: Produto | C18: Tipo | D18: Quantidade | E18: Preço Unitário (R$) | F18: Valor Total (R$) | G18: Custo Total (R$) | H18: Lucro Bruto (R$) | I18: Canal de Venda | J18: Observações
A19: 46098 | B19: DIFUSOR NARDO | C19: Venda | D19: 0 | E19: 159.9 | F19: 0 | G19: =IF(OR(B19="",D19=""),"",IFERROR(D19*VLOOKUP(B19,Produtos!$A$4:$I$13,9,FALSE),"")) -> 0 | H19: =IF(C19="Venda",IF(OR(F19="",G19=""),"",F19-G19),"") -> 0 | I19: Loja
A20: 46098 | B20: DIFUSOR ACACIA | C20: Venda | D20: 0 | E20: 159.9 | F20: 0 | G20: =IF(OR(B20="",D20=""),"",IFERROR(D20*VLOOKUP(B20,Produtos!$A$4:$I$13,9,FALSE),"")) -> 0 | H20: =IF(C20="Venda",IF(OR(F20="",G20=""),"",F20-G20),"") -> 0 | I20: Loja
A21: 46098 | B21: SABONETE NARDO | C21: Venda | D21: 0 | E21: 129.9 | F21: =IF(OR(D21="",E21=""),"",D21*E21) -> 0 | G21: =IF(OR(B21="",D21=""),"",IFERROR(D21*VLOOKUP(B21,Produtos!$A$4:$I$13,9,FALSE),"")) -> 0 | H21: =IF(C21="Venda",IF(OR(F21="",G21=""),"",F21-G21),"") -> 0 | I21: Loja
A22: 46098 | B22: SABONETE ACÁCIA | C22: Venda | D22: 0 | E22: 129.9 | F22: =IF(OR(D22="",E22=""),"",D22*E22) -> 0 | G22: =IF(OR(B22="",D22=""),"",IFERROR(D22*VLOOKUP(B22,Produtos!$A$4:$I$13,9,FALSE),"")) -> 0 | H22: =IF(C22="Venda",IF(OR(F22="",G22=""),"",F22-G22),"") -> 0 | I22: Loja
A23: 46098 | B23: HOME SPRAY AMENDOA | C23: Venda | D23: 0 | E23: 55.5 | F23: 0 | G23: =IF(OR(B23="",D23=""),"",IFERROR(D23*VLOOKUP(B23,Produtos!$A$4:$I$13,9,FALSE),"")) -> 0 | H23: =IF(C23="Venda",IF(OR(F23="",G23=""),"",F23-G23),"") -> 0 | I23: Loja
A24: 46098 | B24: HOME SPRAY SANDALO | C24: Venda | D24: 0 | E24: 55.5 | F24: 0 | G24: =IF(OR(B24="",D24=""),"",IFERROR(D24*VLOOKUP(B24,Produtos!$A$4:$I$13,9,FALSE),"")) -> 0 | H24: =IF(C24="Venda",IF(OR(F24="",G24=""),"",F24-G24),"") -> 0 | I24: Loja
A25: 46098 | B25: BODY SPLASH FIGO | C25: Venda | D25: 0 | E25: 79 | F25: =IF(OR(D25="",E25=""),"",D25*E25) -> 0 | G25: =IF(OR(B25="",D25=""),"",IFERROR(D25*VLOOKUP(B25,Produtos!$A$4:$I$13,9,FALSE),"")) -> 0 | H25: =IF(C25="Venda",IF(OR(F25="",G25=""),"",F25-G25),"") -> 0 | I25: Loja
A26: 46098 | B26: BODY SPLASH ROMÃ | C26: Venda | D26: 0 | E26: 79 | F26: =IF(OR(D26="",E26=""),"",D26*E26) -> 0 | G26: =IF(OR(B26="",D26=""),"",IFERROR(D26*VLOOKUP(B26,Produtos!$A$4:$I$13,9,FALSE),"")) -> 0 | H26: =IF(C26="Venda",IF(OR(F26="",G26=""),"",F26-G26),"") -> 0 | I26: Loja
A27: 46098 | B27: REFIL SABONETE NARDO | C27: Venda | D27: 0 | E27: 46 | F27: =IF(OR(D27="",E27=""),"",D27*E27) -> 0 | G27: =IF(OR(B27="",D27=""),"",IFERROR(D27*VLOOKUP(B27,Produtos!$A$4:$I$13,9,FALSE),"")) -> 0 | H27: =IF(C27="Venda",IF(OR(F27="",G27=""),"",F27-G27),"") -> 0 | I27: Loja
A28: 46098 | B28: REFIL SABONETE ACÁCIA | C28: Venda | D28: 0 | E28: 46 | F28: =IF(OR(D28="",E28=""),"",D28*E28) -> 0 | G28: =IF(OR(B28="",D28=""),"",IFERROR(D28*VLOOKUP(B28,Produtos!$A$4:$I$13,9,FALSE),"")) -> 0 | H28: =IF(C28="Venda",IF(OR(F28="",G28=""),"",F28-G28),"") -> 0 | I28: Loja
A29: 46098 | B29: REFIL DIFUSOR NARDO | C29: Venda | D29: 1 | E29: 86 | F29: =IF(OR(D29="",E29=""),"",D29*E29) -> 86 | G29: =IF(OR(B29="",D29=""),"",IFERROR(D29*VLOOKUP(B29,Produtos!$A$4:$I$13,9,FALSE),"")) | H29: =IF(C29="Venda",IF(OR(F29="",G29=""),"",F29-G29),"") | I29: Loja
A30: 46098 | B30: REFIL DIFUSOR ACÁCIA | C30: Venda | D30: 0 | E30: 86 | F30: =IF(OR(D30="",E30=""),"",D30*E30) -> 0 | G30: =IF(OR(B30="",D30=""),"",IFERROR(D30*VLOOKUP(B30,Produtos!$A$4:$I$13,9,FALSE),"")) | H30: =IF(C30="Venda",IF(OR(F30="",G30=""),"",F30-G30),"") | I30: Loja
E31: =IF(B31="","",IFERROR(VLOOKUP(B31,Produtos!$A$4:$I$13,8,FALSE),"")) | F31: =SUM(F20:F30) -> 86 | G31: =IF(OR(B31="",D31=""),"",IFERROR(D31*VLOOKUP(B31,Produtos!$A$4:$I$13,9,FALSE),"")) | H31: =IF(C31="Venda",IF(OR(F31="",G31=""),"",F31-G31),"")
E32: =IF(B32="","",IFERROR(VLOOKUP(B32,Produtos!$A$4:$I$13,8,FALSE),"")) | F32: =IF(OR(D32="",E32=""),"",D32*E32) | G32: =IF(OR(B32="",D32=""),"",IFERROR(D32*VLOOKUP(B32,Produtos!$A$4:$I$13,9,FALSE),"")) | H32: =IF(C32="Venda",IF(OR(F32="",G32=""),"",F32-G32),"")
E33: =IF(B33="","",IFERROR(VLOOKUP(B33,Produtos!$A$4:$I$13,8,FALSE),"")) | F33: =IF(OR(D33="",E33=""),"",D33*E33) | G33: =IF(OR(B33="",D33=""),"",IFERROR(D33*VLOOKUP(B33,Produtos!$A$4:$I$13,9,FALSE),"")) | H33: =IF(C33="Venda",IF(OR(F33="",G33=""),"",F33-G33),"")
A34: Data | B34: Produto | C34: Tipo | D34: Quantidade | E34: Preço Unitário (R$) | F34: Valor Total (R$) | G34: Custo Total (R$) | H34: Lucro Bruto (R$) | I34: Canal de Venda | J34: Observações
A35: 46100 | B35: DIFUSOR NARDO | C35: Venda | D35: 1 | E35: 159.9 | F35: 159.9 | G35: =IF(OR(B35="",D35=""),"",IFERROR(D35*VLOOKUP(B35,Produtos!$A$4:$I$13,9,FALSE),"")) -> 63.64 | H35: =IF(C35="Venda",IF(OR(F35="",G35=""),"",F35-G35),"") -> 96.26 | I35: Loja
A36: 46100 | B36: DIFUSOR ACACIA | C36: Venda | D36: 0 | E36: 159.9 | F36: 0 | G36: =IF(OR(B36="",D36=""),"",IFERROR(D36*VLOOKUP(B36,Produtos!$A$4:$I$13,9,FALSE),"")) -> 0 | H36: =IF(C36="Venda",IF(OR(F36="",G36=""),"",F36-G36),"") -> 0 | I36: Loja
A37: 46100 | B37: SABONETE NARDO | C37: Venda | D37: 0 | E37: 129.9 | F37: =IF(OR(D37="",E37=""),"",D37*E37) -> 0 | G37: =IF(OR(B37="",D37=""),"",IFERROR(D37*VLOOKUP(B37,Produtos!$A$4:$I$13,9,FALSE),"")) -> 0 | H37: =IF(C37="Venda",IF(OR(F37="",G37=""),"",F37-G37),"") -> 0 | I37: Loja
A38: 46100 | B38: SABONETE ACÁCIA | C38: Venda | D38: 0 | E38: 129.9 | F38: =IF(OR(D38="",E38=""),"",D38*E38) -> 0 | G38: =IF(OR(B38="",D38=""),"",IFERROR(D38*VLOOKUP(B38,Produtos!$A$4:$I$13,9,FALSE),"")) -> 0 | H38: =IF(C38="Venda",IF(OR(F38="",G38=""),"",F38-G38),"") -> 0 | I38: Loja
A39: 46100 | B39: HOME SPRAY AMENDOA | C39: Venda | D39: 0 | E39: 55.5 | F39: 0 | G39: =IF(OR(B39="",D39=""),"",IFERROR(D39*VLOOKUP(B39,Produtos!$A$4:$I$13,9,FALSE),"")) -> 0 | H39: =IF(C39="Venda",IF(OR(F39="",G39=""),"",F39-G39),"") -> 0 | I39: Loja
A40: 46100 | B40: HOME SPRAY SANDALO | C40: Venda | D40: 0 | E40: 55.5 | F40: 0 | G40: =IF(OR(B40="",D40=""),"",IFERROR(D40*VLOOKUP(B40,Produtos!$A$4:$I$13,9,FALSE),"")) -> 0 | H40: =IF(C40="Venda",IF(OR(F40="",G40=""),"",F40-G40),"") -> 0 | I40: Loja
A41: 46100 | B41: BODY SPLASH FIGO | C41: Venda | D41: 0 | E41: 79 | F41: =IF(OR(D41="",E41=""),"",D41*E41) -> 0 | G41: =IF(OR(B41="",D41=""),"",IFERROR(D41*VLOOKUP(B41,Produtos!$A$4:$I$13,9,FALSE),"")) -> 0 | H41: =IF(C41="Venda",IF(OR(F41="",G41=""),"",F41-G41),"") -> 0 | I41: Loja
A42: 46100 | B42: BODY SPLASH ROMÃ | C42: Venda | D42: 0 | E42: 79 | F42: =IF(OR(D42="",E42=""),"",D42*E42) -> 0 | G42: =IF(OR(B42="",D42=""),"",IFERROR(D42*VLOOKUP(B42,Produtos!$A$4:$I$13,9,FALSE),"")) -> 0 | H42: =IF(C42="Venda",IF(OR(F42="",G42=""),"",F42-G42),"") -> 0 | I42: Loja
A43: 46100 | B43: REFIL SABONETE NARDO | C43: Venda | D43: 0 | E43: 46 | F43: =IF(OR(D43="",E43=""),"",D43*E43) -> 0 | G43: =IF(OR(B43="",D43=""),"",IFERROR(D43*VLOOKUP(B43,Produtos!$A$4:$I$13,9,FALSE),"")) -> 0 | H43: =IF(C43="Venda",IF(OR(F43="",G43=""),"",F43-G43),"") -> 0 | I43: Loja
A44: 46100 | B44: REFIL SABONETE ACÁCIA | C44: Venda | D44: 0 | E44: 46 | F44: =IF(OR(D44="",E44=""),"",D44*E44) -> 0 | G44: =IF(OR(B44="",D44=""),"",IFERROR(D44*VLOOKUP(B44,Produtos!$A$4:$I$13,9,FALSE),"")) -> 0 | H44: =IF(C44="Venda",IF(OR(F44="",G44=""),"",F44-G44),"") -> 0 | I44: Loja
A45: 46100 | B45: REFIL DIFUSOR NARDO | C45: Venda | D45: 1 | E45: 86 | F45: =IF(OR(D45="",E45=""),"",D45*E45) -> 86 | G45: =IF(OR(B45="",D45=""),"",IFERROR(D45*VLOOKUP(B45,Produtos!$A$4:$I$13,9,FALSE),"")) | H45: =IF(C45="Venda",IF(OR(F45="",G45=""),"",F45-G45),"") | I45: Loja
A46: 46100 | B46: REFIL DIFUSOR ACÁCIA | C46: Venda | D46: 1 | E46: 86 | F46: =IF(OR(D46="",E46=""),"",D46*E46) -> 86 | G46: =IF(OR(B46="",D46=""),"",IFERROR(D46*VLOOKUP(B46,Produtos!$A$4:$I$13,9,FALSE),"")) | H46: =IF(C46="Venda",IF(OR(F46="",G46=""),"",F46-G46),"") | I46: Loja
E47: =IF(B47="","",IFERROR(VLOOKUP(B47,Produtos!$A$4:$I$13,8,FALSE),"")) | F47: =SUM(F35:F46) -> 331.9 | G47: =IF(OR(B47="",D47=""),"",IFERROR(D47*VLOOKUP(B47,Produtos!$A$4:$I$13,9,FALSE),"")) | H47: =IF(C47="Venda",IF(OR(F47="",G47=""),"",F47-G47),"")
E48: =IF(B48="","",IFERROR(VLOOKUP(B48,Produtos!$A$4:$I$13,8,FALSE),"")) | F48: =IF(OR(D48="",E48=""),"",D48*E48) | G48: =IF(OR(B48="",D48=""),"",IFERROR(D48*VLOOKUP(B48,Produtos!$A$4:$I$13,9,FALSE),"")) | H48: =IF(C48="Venda",IF(OR(F48="",G48=""),"",F48-G48),"")
E49: =IF(B49="","",IFERROR(VLOOKUP(B49,Produtos!$A$4:$I$13,8,FALSE),"")) | F49: =IF(OR(D49="",E49=""),"",D49*E49) | G49: =IF(OR(B49="",D49=""),"",IFERROR(D49*VLOOKUP(B49,Produtos!$A$4:$I$13,9,FALSE),"")) | H49: =IF(C49="Venda",IF(OR(F49="",G49=""),"",F49-G49),"")
A50: Data | B50: Produto | C50: Tipo | D50: Quantidade | E50: Preço Unitário (R$) | F50: Valor Total (R$) | G50: Custo Total (R$) | H50: Lucro Bruto (R$) | I50: Canal de Venda | J50: Observações
A51: 46101 | B51: DIFUSOR NARDO | C51: Venda | D51: 0 | E51: 159.9 | F51: 0 | G51: =IF(OR(B51="",D51=""),"",IFERROR(D51*VLOOKUP(B51,Produtos!$A$4:$I$13,9,FALSE),"")) -> 0 | H51: =IF(C51="Venda",IF(OR(F51="",G51=""),"",F51-G51),"") -> 0 | I51: Loja
A52: 46101 | B52: DIFUSOR ACACIA | C52: Venda | D52: 0 | E52: 159.9 | F52: 0 | G52: =IF(OR(B52="",D52=""),"",IFERROR(D52*VLOOKUP(B52,Produtos!$A$4:$I$13,9,FALSE),"")) -> 0 | H52: =IF(C52="Venda",IF(OR(F52="",G52=""),"",F52-G52),"") -> 0 | I52: Loja
A53: 46101 | B53: SABONETE NARDO | C53: Venda | D53: 1 | E53: 129.9 | F53: =IF(OR(D53="",E53=""),"",D53*E53) -> 129.9 | G53: =IF(OR(B53="",D53=""),"",IFERROR(D53*VLOOKUP(B53,Produtos!$A$4:$I$13,9,FALSE),"")) -> 47.73 | H53: =IF(C53="Venda",IF(OR(F53="",G53=""),"",F53-G53),"") -> 82.17 | I53: Loja
A54: 46101 | B54: SABONETE ACÁCIA | C54: Venda | D54: 0 | E54: 129.9 | F54: =IF(OR(D54="",E54=""),"",D54*E54) -> 0 | G54: =IF(OR(B54="",D54=""),"",IFERROR(D54*VLOOKUP(B54,Produtos!$A$4:$I$13,9,FALSE),"")) -> 0 | H54: =IF(C54="Venda",IF(OR(F54="",G54=""),"",F54-G54),"") -> 0 | I54: Loja
A55: 46101 | B55: HOME SPRAY AMENDOA | C55: Venda | D55: 0 | E55: 55.5 | F55: 0 | G55: =IF(OR(B55="",D55=""),"",IFERROR(D55*VLOOKUP(B55,Produtos!$A$4:$I$13,9,FALSE),"")) -> 0 | H55: =IF(C55="Venda",IF(OR(F55="",G55=""),"",F55-G55),"") -> 0 | I55: Loja
A56: 46101 | B56: HOME SPRAY SANDALO | C56: Venda | D56: 0 | E56: 55.5 | F56: 0 | G56: =IF(OR(B56="",D56=""),"",IFERROR(D56*VLOOKUP(B56,Produtos!$A$4:$I$13,9,FALSE),"")) -> 0 | H56: =IF(C56="Venda",IF(OR(F56="",G56=""),"",F56-G56),"") -> 0 | I56: Loja
A57: 46101 | B57: BODY SPLASH FIGO | C57: Venda | D57: 0 | E57: 79 | F57: =IF(OR(D57="",E57=""),"",D57*E57) -> 0 | G57: =IF(OR(B57="",D57=""),"",IFERROR(D57*VLOOKUP(B57,Produtos!$A$4:$I$13,9,FALSE),"")) -> 0 | H57: =IF(C57="Venda",IF(OR(F57="",G57=""),"",F57-G57),"") -> 0 | I57: Loja
A58: 46101 | B58: BODY SPLASH ROMÃ | C58: Venda | D58: 0 | E58: 79 | F58: =IF(OR(D58="",E58=""),"",D58*E58) -> 0 | G58: =IF(OR(B58="",D58=""),"",IFERROR(D58*VLOOKUP(B58,Produtos!$A$4:$I$13,9,FALSE),"")) -> 0 | H58: =IF(C58="Venda",IF(OR(F58="",G58=""),"",F58-G58),"") -> 0 | I58: Loja
A59: 46101 | B59: REFIL SABONETE NARDO | C59: Venda | D59: 0 | E59: 46 | F59: =IF(OR(D59="",E59=""),"",D59*E59) -> 0 | G59: =IF(OR(B59="",D59=""),"",IFERROR(D59*VLOOKUP(B59,Produtos!$A$4:$I$13,9,FALSE),"")) -> 0 | H59: =IF(C59="Venda",IF(OR(F59="",G59=""),"",F59-G59),"") -> 0 | I59: Loja
A60: 46101 | B60: REFIL SABONETE ACÁCIA | C60: Venda | D60: 0 | E60: 46 | F60: =IF(OR(D60="",E60=""),"",D60*E60) -> 0 | G60: =IF(OR(B60="",D60=""),"",IFERROR(D60*VLOOKUP(B60,Produtos!$A$4:$I$13,9,FALSE),"")) -> 0 | H60: =IF(C60="Venda",IF(OR(F60="",G60=""),"",F60-G60),"") -> 0 | I60: Loja
A61: 46101 | B61: REFIL DIFUSOR NARDO | C61: Venda | D61: 0 | E61: 86 | F61: =IF(OR(D61="",E61=""),"",D61*E61) -> 0 | G61: =IF(OR(B61="",D61=""),"",IFERROR(D61*VLOOKUP(B61,Produtos!$A$4:$I$13,9,FALSE),"")) | H61: =IF(C61="Venda",IF(OR(F61="",G61=""),"",F61-G61),"") | I61: Loja
A62: 46101 | B62: REFIL DIFUSOR ACÁCIA | C62: Venda | D62: 0 | E62: 86 | F62: =IF(OR(D62="",E62=""),"",D62*E62) -> 0 | G62: =IF(OR(B62="",D62=""),"",IFERROR(D62*VLOOKUP(B62,Produtos!$A$4:$I$13,9,FALSE),"")) | H62: =IF(C62="Venda",IF(OR(F62="",G62=""),"",F62-G62),"") | I62: Loja
E63: =IF(B63="","",IFERROR(VLOOKUP(B63,Produtos!$A$4:$I$13,8,FALSE),"")) | F63: =SUM(F52:F62) -> 129.9 | G63: =IF(OR(B63="",D63=""),"",IFERROR(D63*VLOOKUP(B63,Produtos!$A$4:$I$13,9,FALSE),"")) | H63: =IF(C63="Venda",IF(OR(F63="",G63=""),"",F63-G63),"")
E64: =IF(B64="","",IFERROR(VLOOKUP(B64,Produtos!$A$4:$I$13,8,FALSE),"")) | F64: =IF(OR(D64="",E64=""),"",D64*E64) | G64: =IF(OR(B64="",D64=""),"",IFERROR(D64*VLOOKUP(B64,Produtos!$A$4:$I$13,9,FALSE),"")) | H64: =IF(C64="Venda",IF(OR(F64="",G64=""),"",F64-G64),"")
E65: =IF(B65="","",IFERROR(VLOOKUP(B65,Produtos!$A$4:$I$13,8,FALSE),"")) | F65: =IF(OR(D65="",E65=""),"",D65*E65) | G65: =IF(OR(B65="",D65=""),"",IFERROR(D65*VLOOKUP(B65,Produtos!$A$4:$I$13,9,FALSE),"")) | H65: =IF(C65="Venda",IF(OR(F65="",G65=""),"",F65-G65),"")
A66: Data | B66: Produto | C66: Tipo | D66: Quantidade | E66: Preço Unitário (R$) | F66: Valor Total (R$) | G66: Custo Total (R$) | H66: Lucro Bruto (R$) | I66: Canal de Venda | J66: Observações
A67: 46105 | B67: DIFUSOR NARDO | C67: Venda | D67: 1 | E67: 159.9 | F67: =IF(OR(D67="",E67=""),"",D67*E67) -> 159.9 | G67: =IF(OR(B67="",D67=""),"",IFERROR(D67*VLOOKUP(B67,Produtos!$A$4:$I$13,9,FALSE),"")) -> 63.64 | H67: =IF(C67="Venda",IF(OR(F67="",G67=""),"",F67-G67),"") -> 96.26 | I67: Loja
A68: 46105 | B68: DIFUSOR ACACIA | C68: Venda | D68: 0 | E68: 159.9 | F68: =IF(OR(D68="",E68=""),"",D68*E68) -> 0 | G68: =IF(OR(B68="",D68=""),"",IFERROR(D68*VLOOKUP(B68,Produtos!$A$4:$I$13,9,FALSE),"")) -> 0 | H68: =IF(C68="Venda",IF(OR(F68="",G68=""),"",F68-G68),"") -> 0 | I68: Loja
A69: 46105 | B69: SABONETE NARDO | C69: Venda | D69: 0 | E69: 129.9 | F69: =IF(OR(D69="",E69=""),"",D69*E69) -> 0 | G69: =IF(OR(B69="",D69=""),"",IFERROR(D69*VLOOKUP(B69,Produtos!$A$4:$I$13,9,FALSE),"")) -> 0 | H69: =IF(C69="Venda",IF(OR(F69="",G69=""),"",F69-G69),"") -> 0 | I69: Loja
A70: 46105 | B70: SABONETE ACÁCIA | C70: Venda | D70: 0 | E70: 129.9 | F70: =IF(OR(D70="",E70=""),"",D70*E70) -> 0 | G70: =IF(OR(B70="",D70=""),"",IFERROR(D70*VLOOKUP(B70,Produtos!$A$4:$I$13,9,FALSE),"")) -> 0 | H70: =IF(C70="Venda",IF(OR(F70="",G70=""),"",F70-G70),"") -> 0 | I70: Loja
A71: 46105 | B71: HOME SPRAY AMENDOA | C71: Venda | D71: 2 | E71: 55.5 | F71: =IF(OR(D71="",E71=""),"",D71*E71) -> 111 | G71: =IF(OR(B71="",D71=""),"",IFERROR(D71*VLOOKUP(B71,Produtos!$A$4:$I$13,9,FALSE),"")) -> 43.98 | H71: =IF(C71="Venda",IF(OR(F71="",G71=""),"",F71-G71),"") -> 67.02 | I71: Loja
A72: 46105 | B72: HOME SPRAY SANDALO | C72: Venda | D72: 2 | E72: 55.5 | F72: =IF(OR(D72="",E72=""),"",D72*E72) -> 111 | G72: =IF(OR(B72="",D72=""),"",IFERROR(D72*VLOOKUP(B72,Produtos!$A$4:$I$13,9,FALSE),"")) -> 43.98 | H72: =IF(C72="Venda",IF(OR(F72="",G72=""),"",F72-G72),"") -> 67.02 | I72: Loja
A73: 46105 | B73: BODY SPLASH FIGO | C73: Venda | D73: 4 | E73: 79 | F73: =IF(OR(D73="",E73=""),"",D73*E73) -> 316 | G73: =IF(OR(B73="",D73=""),"",IFERROR(D73*VLOOKUP(B73,Produtos!$A$4:$I$13,9,FALSE),"")) -> 114.72 | H73: =IF(C73="Venda",IF(OR(F73="",G73=""),"",F73-G73),"") -> 201.28 | I73: Loja
A74: 46105 | B74: BODY SPLASH ROMÃ | C74: Venda | D74: 5 | E74: 79 | F74: =IF(OR(D74="",E74=""),"",D74*E74) -> 395 | G74: =IF(OR(B74="",D74=""),"",IFERROR(D74*VLOOKUP(B74,Produtos!$A$4:$I$13,9,FALSE),"")) -> 143.4 | H74: =IF(C74="Venda",IF(OR(F74="",G74=""),"",F74-G74),"") -> 251.6 | I74: Loja
A75: 46105 | B75: REFIL SABONETE NARDO | C75: Venda | D75: 0 | E75: 46 | F75: =IF(OR(D75="",E75=""),"",D75*E75) -> 0 | G75: =IF(OR(B75="",D75=""),"",IFERROR(D75*VLOOKUP(B75,Produtos!$A$4:$I$13,9,FALSE),"")) -> 0 | H75: =IF(C75="Venda",IF(OR(F75="",G75=""),"",F75-G75),"") -> 0 | I75: Loja
A76: 46105 | B76: REFIL SABONETE ACÁCIA | C76: Venda | D76: 0 | E76: 46 | F76: =IF(OR(D76="",E76=""),"",D76*E76) -> 0 | G76: =IF(OR(B76="",D76=""),"",IFERROR(D76*VLOOKUP(B76,Produtos!$A$4:$I$13,9,FALSE),"")) -> 0 | H76: =IF(C76="Venda",IF(OR(F76="",G76=""),"",F76-G76),"") -> 0 | I76: Loja
A77: 46105 | B77: REFIL DIFUSOR NARDO | C77: Venda | D77: 1 | E77: 86 | F77: =IF(OR(D77="",E77=""),"",D77*E77) -> 86 | G77: =IF(OR(B77="",D77=""),"",IFERROR(D77*VLOOKUP(B77,Produtos!$A$4:$I$13,9,FALSE),"")) | H77: =IF(C77="Venda",IF(OR(F77="",G77=""),"",F77-G77),"") | I77: Loja
A78: 46105 | B78: REFIL DIFUSOR ACÁCIA | C78: Venda | D78: 0 | E78: 86 | F78: =IF(OR(D78="",E78=""),"",D78*E78) -> 0 | G78: =IF(OR(B78="",D78=""),"",IFERROR(D78*VLOOKUP(B78,Produtos!$A$4:$I$13,9,FALSE),"")) | H78: =IF(C78="Venda",IF(OR(F78="",G78=""),"",F78-G78),"") | I78: Loja
E79: =IF(B79="","",IFERROR(VLOOKUP(B79,Produtos!$A$4:$I$13,8,FALSE),"")) | F79: =SUM(F68:F78) -> 1019 | G79: =IF(OR(B79="",D79=""),"",IFERROR(D79*VLOOKUP(B79,Produtos!$A$4:$I$13,9,FALSE),"")) | H79: =IF(C79="Venda",IF(OR(F79="",G79=""),"",F79-G79),"")
E80: =IF(B80="","",IFERROR(VLOOKUP(B80,Produtos!$A$4:$I$13,8,FALSE),"")) | F80: =IF(OR(D80="",E80=""),"",D80*E80) | G80: =IF(OR(B80="",D80=""),"",IFERROR(D80*VLOOKUP(B80,Produtos!$A$4:$I$13,9,FALSE),"")) | H80: =IF(C80="Venda",IF(OR(F80="",G80=""),"",F80-G80),"")
E81: =IF(B81="","",IFERROR(VLOOKUP(B81,Produtos!$A$4:$I$13,8,FALSE),"")) | F81: =IF(OR(D81="",E81=""),"",D81*E81) | G81: =IF(OR(B81="",D81=""),"",IFERROR(D81*VLOOKUP(B81,Produtos!$A$4:$I$13,9,FALSE),"")) | H81: =IF(C81="Venda",IF(OR(F81="",G81=""),"",F81-G81),"")
E82: =IF(B82="","",IFERROR(VLOOKUP(B82,Produtos!$A$4:$I$13,8,FALSE),"")) | F82: =IF(OR(D82="",E82=""),"",D82*E82) | G82: =IF(OR(B82="",D82=""),"",IFERROR(D82*VLOOKUP(B82,Produtos!$A$4:$I$13,9,FALSE),"")) | H82: =IF(C82="Venda",IF(OR(F82="",G82=""),"",F82-G82),"")
E83: =IF(B83="","",IFERROR(VLOOKUP(B83,Produtos!$A$4:$I$13,8,FALSE),"")) | F83: =IF(OR(D83="",E83=""),"",D83*E83) | G83: =IF(OR(B83="",D83=""),"",IFERROR(D83*VLOOKUP(B83,Produtos!$A$4:$I$13,9,FALSE),"")) | H83: =IF(C83="Venda",IF(OR(F83="",G83=""),"",F83-G83),"")
E84: =IF(B84="","",IFERROR(VLOOKUP(B84,Produtos!$A$4:$I$13,8,FALSE),"")) | F84: =IF(OR(D84="",E84=""),"",D84*E84) | G84: =IF(OR(B84="",D84=""),"",IFERROR(D84*VLOOKUP(B84,Produtos!$A$4:$I$13,9,FALSE),"")) | H84: =IF(C84="Venda",IF(OR(F84="",G84=""),"",F84-G84),"")
E85: =IF(B85="","",IFERROR(VLOOKUP(B85,Produtos!$A$4:$I$13,8,FALSE),"")) | F85: =IF(OR(D85="",E85=""),"",D85*E85) | G85: =IF(OR(B85="",D85=""),"",IFERROR(D85*VLOOKUP(B85,Produtos!$A$4:$I$13,9,FALSE),"")) | H85: =IF(C85="Venda",IF(OR(F85="",G85=""),"",F85-G85),"")
E86: =IF(B86="","",IFERROR(VLOOKUP(B86,Produtos!$A$4:$I$13,8,FALSE),"")) | F86: =IF(OR(D86="",E86=""),"",D86*E86) | G86: =IF(OR(B86="",D86=""),"",IFERROR(D86*VLOOKUP(B86,Produtos!$A$4:$I$13,9,FALSE),"")) | H86: =IF(C86="Venda",IF(OR(F86="",G86=""),"",F86-G86),"")
E87: =IF(B87="","",IFERROR(VLOOKUP(B87,Produtos!$A$4:$I$13,8,FALSE),"")) | F87: =IF(OR(D87="",E87=""),"",D87*E87) | G87: =IF(OR(B87="",D87=""),"",IFERROR(D87*VLOOKUP(B87,Produtos!$A$4:$I$13,9,FALSE),"")) | H87: =IF(C87="Venda",IF(OR(F87="",G87=""),"",F87-G87),"")
E88: =IF(B88="","",IFERROR(VLOOKUP(B88,Produtos!$A$4:$I$13,8,FALSE),"")) | F88: =IF(OR(D88="",E88=""),"",D88*E88) | G88: =IF(OR(B88="",D88=""),"",IFERROR(D88*VLOOKUP(B88,Produtos!$A$4:$I$13,9,FALSE),"")) | H88: =IF(C88="Venda",IF(OR(F88="",G88=""),"",F88-G88),"")
E89: =IF(B89="","",IFERROR(VLOOKUP(B89,Produtos!$A$4:$I$13,8,FALSE),"")) | F89: =IF(OR(D89="",E89=""),"",D89*E89) | G89: =IF(OR(B89="",D89=""),"",IFERROR(D89*VLOOKUP(B89,Produtos!$A$4:$I$13,9,FALSE),"")) | H89: =IF(C89="Venda",IF(OR(F89="",G89=""),"",F89-G89),"")
E90: =IF(B90="","",IFERROR(VLOOKUP(B90,Produtos!$A$4:$I$13,8,FALSE),"")) | F90: =IF(OR(D90="",E90=""),"",D90*E90) | G90: =IF(OR(B90="",D90=""),"",IFERROR(D90*VLOOKUP(B90,Produtos!$A$4:$I$13,9,FALSE),"")) | H90: =IF(C90="Venda",IF(OR(F90="",G90=""),"",F90-G90),"")
E91: =IF(B91="","",IFERROR(VLOOKUP(B91,Produtos!$A$4:$I$13,8,FALSE),"")) | F91: =IF(OR(D91="",E91=""),"",D91*E91) | G91: =IF(OR(B91="",D91=""),"",IFERROR(D91*VLOOKUP(B91,Produtos!$A$4:$I$13,9,FALSE),"")) | H91: =IF(C91="Venda",IF(OR(F91="",G91=""),"",F91-G91),"")
... E104: =IF(B104="","",IFERROR(VLOOKUP(B104,Produtos!$A$4:$I$13,8,FALSE),"")) | F104: =IF(OR(D104="",E104=""),"",D104*E104) | G104: =IF(OR(B104="",D104=""),"",IFERROR(D104*VLOOKUP(B104,Produtos!$A$4:$I$13,9,FALSE),"")) | H104: =IF(C104="Venda",IF(OR(F104="",G104=""),"",F104-G104),"")

Sheet Financeiro
A1: BAUMEVIE | Resumo Financeiro e Canais
A3: Canal | B3: Faturamento (R$) | C3: Itens Vendidos | D3: Lucro Bruto (R$) | E3: Ticket Médio (R$) | F3: Meta Mensal (R$) | G3: Atingimento | H3: Observação | J3: Faturamento Total
A4: Instagram | B4: =SUMIFS('Vendas diárias'!$F:$F,'Vendas diárias'!$I:$I,$A4,'Vendas diárias'!$C:$C,"Venda") -> 0 | C4: =SUMIFS('Vendas diárias'!$D:$D,'Vendas diárias'!$I:$I,$A4,'Vendas diárias'!$C:$C,"Venda") -> 0 | D4: =SUMIFS('Vendas diárias'!$H:$H,'Vendas diárias'!$I:$I,$A4) -> 0 | E4: =IFERROR(B4/COUNTIFS('Vendas diárias'!$I:$I,$A4,'Vendas diárias'!$C:$C,"Venda"),0) -> 0 | F4: 1000 | G4: =IFERROR(B4/F4,0) -> 0 | J4: =SUMIFS('Vendas diárias'!F:F,'Vendas diárias'!C:C,"Venda") -> 2052.7
A5: WhatsApp | B5: =SUMIFS('Vendas diárias'!$F:$F,'Vendas diárias'!$I:$I,$A5,'Vendas diárias'!$C:$C,"Venda") -> 0 | C5: =SUMIFS('Vendas diárias'!$D:$D,'Vendas diárias'!$I:$I,$A5,'Vendas diárias'!$C:$C,"Venda") -> 0 | D5: =SUMIFS('Vendas diárias'!$H:$H,'Vendas diárias'!$I:$I,$A5) -> 0 | E5: =IFERROR(B5/COUNTIFS('Vendas diárias'!$I:$I,$A5,'Vendas diárias'!$C:$C,"Venda"),0) -> 0 | F5: 1000 | G5: =IFERROR(B5/F5,0) -> 0 | J5: Lucro Bruto Total
A6: Site | B6: =SUMIFS('Vendas diárias'!$F:$F,'Vendas diárias'!$I:$I,$A6,'Vendas diárias'!$C:$C,"Venda") -> 0 | C6: =SUMIFS('Vendas diárias'!$D:$D,'Vendas diárias'!$I:$I,$A6,'Vendas diárias'!$C:$C,"Venda") -> 0 | D6: =SUMIFS('Vendas diárias'!$H:$H,'Vendas diárias'!$I:$I,$A6) -> 0 | E6: =IFERROR(B6/COUNTIFS('Vendas diárias'!$I:$I,$A6,'Vendas diárias'!$C:$C,"Venda"),0) -> 0 | F6: 1000 | G6: =IFERROR(B6/F6,0) -> 0 | J6: =SUM('Vendas diárias'!H:H) -> 993.99
A7: Feira | B7: =SUMIFS('Vendas diárias'!$F:$F,'Vendas diárias'!$I:$I,$A7,'Vendas diárias'!$C:$C,"Venda") -> 0 | C7: =SUMIFS('Vendas diárias'!$D:$D,'Vendas diárias'!$I:$I,$A7,'Vendas diárias'!$C:$C,"Venda") -> 0 | D7: =SUMIFS('Vendas diárias'!$H:$H,'Vendas diárias'!$I:$I,$A7) -> 0 | E7: =IFERROR(B7/COUNTIFS('Vendas diárias'!$I:$I,$A7,'Vendas diárias'!$C:$C,"Venda"),0) -> 0 | F7: 1000 | G7: =IFERROR(B7/F7,0) -> 0 | J7: Ticket Médio Geral
A8: Loja | B8: =SUMIFS('Vendas diárias'!$F:$F,'Vendas diárias'!$I:$I,$A8,'Vendas diárias'!$C:$C,"Venda") -> 2052.7 | C8: =SUMIFS('Vendas diárias'!$D:$D,'Vendas diárias'!$I:$I,$A8,'Vendas diárias'!$C:$C,"Venda") -> 24 | D8: =SUMIFS('Vendas diárias'!$H:$H,'Vendas diárias'!$I:$I,$A8) -> 993.99 | E8: =IFERROR(B8/COUNTIFS('Vendas diárias'!$I:$I,$A8,'Vendas diárias'!$C:$C,"Venda"),0) -> 34.211667 | F8: 1000 | G8: =IFERROR(B8/F8,0) -> 2.0527 | J8: =IFERROR(SUMIFS('Vendas diárias'!F:F,'Vendas diárias'!C:C,"Venda")/COUNTIFS('Vendas diárias'!C:C,"Venda"),0) -> 34.211667
A9: Outro | B9: =SUMIFS('Vendas diárias'!$F:$F,'Vendas diárias'!$I:$I,$A9,'Vendas diárias'!$C:$C,"Venda") -> 0 | C9: =SUMIFS('Vendas diárias'!$D:$D,'Vendas diárias'!$I:$I,$A9,'Vendas diárias'!$C:$C,"Venda") -> 0 | D9: =SUMIFS('Vendas diárias'!$H:$H,'Vendas diárias'!$I:$I,$A9) -> 0 | E9: =IFERROR(B9/COUNTIFS('Vendas diárias'!$I:$I,$A9,'Vendas diárias'!$C:$C,"Venda"),0) -> 0 | F9: 1000 | G9: =IFERROR(B9/F9,0) -> 0 | J9: Produtos para Repor
A10: TOTAL | B10: =SUM(B4:B9) -> 2052.7 | C10: =SUM(C4:C9) -> 24 | D10: =SUM(D4:D9) -> 993.99 | E10: =IFERROR(B10/COUNTIFS('Vendas diárias'!$C:$C,"Venda"),0) -> 34.211667 | F10: =SUM(F4:F9) -> 6000 | G10: =IFERROR(B10/F10,0) -> 0.34211667 | J10: =COUNTIF(Produtos!M4:M13,"REPOR") -> 2

Sheet Resumo
A1: BAUMEVIE | Dashboard Geral
A3: Faturamento Total | C3: Lucro Bruto | E3: Itens Vendidos | G3: Valor em Estoque
A4: =SUMIFS('Vendas diárias'!F:F,'Vendas diárias'!C:C,"Venda") -> 2052.7 | C4: =SUM('Vendas diárias'!H:H) -> 993.99 | E4: =SUMIFS('Vendas diárias'!D:D,'Vendas diárias'!C:C,"Venda") -> 24 | G4: =Produtos!K16 -> 99595.5
A6: Produtos para Repor | C6: Canal Destaque | E6: Ticket Médio | G6: Custo Total
A7: =COUNTIF(Produtos!M4:M13,"REPOR") -> 2 | C7: =INDEX(Financeiro!A4:A9,MATCH(MAX(Financeiro!B4:B9),Financeiro!B4:B9,0)) -> Loja | E7: =IFERROR(SUMIFS('Vendas diárias'!F:F,'Vendas diárias'!C:C,"Venda")/COUNTIFS('Vendas diárias'!C:C,"Venda"),0) -> 34.211667 | G7: =SUM('Vendas diárias'!G:G) -> 628.71
A10: Produtos para acompanhar | G10: Como usar
A11: Produto | B11: Estoque Atual | C11: Status | D11: Preço | E11: Custo | G11: 1. Atualize preços e custos na aba Produtos.
A12: =Produtos!A4 -> DIFUSOR NARDO | B12: =Produtos!G4 -> 171 | C12: =Produtos!M4 -> OK | D12: =Produtos!H4 -> 159.9 | E12: =Produtos!I4 -> 63.64 | G12: 2. Lance cada venda ou entrada na aba Lancamentos.
A13: =Produtos!A5 -> DIFUSOR ACACIA | B13: =Produtos!G5 -> 97 | C13: =Produtos!M5 -> OK | D13: =Produtos!H5 -> 159.9 | E13: =Produtos!I5 -> 63.64 | G13: 3. Veja lucro, canais e metas na aba Financeiro.
A14: =Produtos!A6 -> SABONETE NARDO | B14: =Produtos!G6 -> 165 | C14: =Produtos!M6 -> OK | D14: =Produtos!H6 -> 129.9 | E14: =Produtos!I6 -> 47.73 | G14: 4. O Resumo mostra os principais indicadores.
A15: =Produtos!A7 -> SABONETE ACÁCIA | B15: =Produtos!G7 -> 187 | C15: =Produtos!M7 -> OK | D15: =Produtos!H7 -> 129.9 | E15: =Produtos!I7 -> 47.73
A16: =Produtos!A8 -> HOME SPRAY AMENDOA | B16: =Produtos!G8 -> 33 | C16: =Produtos!M8 -> OK | D16: =Produtos!H8 -> 55.5 | E16: =Produtos!I8 -> 21.99
A17: =Produtos!A9 -> HOME SPRAY SANDALO | B17: =Produtos!G9 -> 16 | C17: =Produtos!M9 -> OK | D17: =Produtos!H9 -> 55.5 | E17: =Produtos!I9 -> 21.99
A18: =Produtos!A10 -> BODY SPLASH FIGO | B18: =Produtos!G10 -> 49 | C18: =Produtos!M10 -> OK | D18: =Produtos!H10 -> 79 | E18: =Produtos!I10 -> 28.68
A19: =Produtos!A11 -> BODY SPLASH ROMÃ | B19: =Produtos!G11 -> 45 | C19: =Produtos!M11 -> OK | D19: =Produtos!H11 -> 79 | E19: =Produtos!I11 -> 28.68
A20: =Produtos!A12 -> REFIL SABONETE NARDO | B20: =Produtos!G12 -> 2 | C20: =Produtos!M12 -> REPOR | D20: =Produtos!H12 -> 46 | E20: =Produtos!I12 -> 33.88
A21: =Produtos!A13 -> REFIL SABONETE ACÁCIA | B21: =Produtos!G13 -> 2 | C21: =Produtos!M13 -> REPOR | D21: =Produtos!H13 -> 46 | E21: =Produtos!I13 -> 33.88

Sheet Vendas
A1: RECEBIMENTO | B1: Valor | C1: Pessoa | D1: Saldo conta
A2: 46081 | B2: 341
A3: 46084 | B3: 1036 | D3: 0
A4: 46086 | B4: =80*2 -> 160
A5: 46087 | B5: 129.9
A6: 46091 | B6: 341
A7: 46094 | B7: 812.4 | C7: Lara | D7: 524 | E7: 46107
A8: 46109 | B8: 812.4 | C8: Lara | D8: =SUM(D7+B8) -> 1336.4 | E8: 46109
A9: 46113 | B9: 129.9 | C9: Cartão | D9: =SUM(D8+B9) -> 1466.3 | E9: 46113
A10: 46113 | B10: 1735.2 | C10: Diversos venda - El Shadai/BA | D10: =SUM(D7+B8+B9+B10) -> 3201.5 | E10: 46113
A11: 46126 | B11: 812.4 | C11: Lara | D11: =SUM(D10+B11) -> 4013.9 | E11: 46126
A12: 46130 | B12: 395.69 | C12: João | D12: =SUM(D11+B12) -> 4409.59 | E12: 46130
A13: 46145 | B13: 395.69 | C13: João | D13: =SUM(D12+B13) -> 4805.28 | E13: 46145
A14: 46160 | B14: 395.69 | C14: João | D14: =SUM(D13+B14) -> 5200.97 | E14: 46160
B19: FIGO | C19: ROMÃ | D19: PAGO | E19: A PAGAR
A20: MARIELA | B20: X | D20: 79
A21: ELYS | B21: X | D21: 79
A22: JOSI ELSHADAI | B22: X | D22: 79
A23: ANGELICA EL SHADAI | B23: X | C23: X | E23: 148 | F23: Entregue em 19/02/26
A24: Angelica 2 refis acácia | E24: 172 | F24: Entregue 08/03
A25: ! Difusor Nardo | E25: 159.9 | F25: Entregar
A26: JOYCE | B26: X | C26: X | D26: 148
A27: JOYCE | B27: X | C27: X | D27: 148 | E27: 0
A28: ROBERTA | C28: X | D28: 79
A29: LILLIANE | B29: X | C29: X | D29: 148 | E29: 0 | F29: Pagará em 20/02
A30: GISELE | B30: X | C30: X | E30: 148 | F30: Pagar final de 02/26
A31: JOY DIFUSOR NARDO | D31: 129.9 | E31: 0
A32: Zefinha refil difusor Nardo | E32: 86 | F32: pagar dia 05/03
A33: JO refil acacia difusor | D33: 172 | E33: 0
A34: Glecia Difusor Acacia | E34: 159.9 | F34: Entregar
A35: Glecia refil difusor Acácia | E35: 86 | F35: Entregar
A37: Claudia | E37: 324.9
A38: CRIS | E38: 158
A39: PRISCILA | E39: 292.5
D41: =SUM(D20:D33) -> 1061.9 | E41: =SUM(E20:E40) -> 1735.2

Sheet Estoque inicio Loja
B1: 46062 | C1: Venda 16/02 | D1: venda 18/02 | E1: Casa mãe | F1: total estoque 19/02 | G1: Venda 19/02 | H1: Venda 20/02 | I1: total 1 semana | J1: venda 24/02 | K1: venda 25/02 | L1: venda 27/02 | M1: ESTOQUE | N1: VENDA 28/02 | O1: ESTOQUE | P1: venda 02/03/26 | Q1: ESTOQUE | R1: Venda 05/03 | S1: Venda 06/03 | T1: TOTAL GERAL | U1: Venda 08/03/26 | V1: venda 10/03/26 | W1: ESTOQUE
A2: DIFUSOR NARDO | B2: 96 | C2: 1 | E2: 87 | F2: =SUM(B2+E2-C2-D2) -> 182 | K2: 8 | M2: =SUM(F2-G2-H2-J2-K2-L2) -> 174 | O2: =SUM(M2-N2) -> 174 | Q2: =SUM(O2-P2) -> 174 | W2: 174
A3: DIFUSOR ACACIA | B3: 44 | C3: 1 | E3: 65 | F3: =SUM(B3+E3-C3-D3) -> 108 | L3: 1 | M3: =SUM(F3-G3-H3-J3-K3-L3) -> 107 | N3: 1 | O3: 101 | P3: 2 | Q3: =SUM(O3-P3) -> 99 | W3: 99
A4: SABONETE NARDO | B4: 50 | C4: 0 | E4: 143 | F4: =SUM(B4+E4-C4-D4) -> 193 | K4: 6 | M4: =SUM(F4-G4-H4-J4-K4-L4)-8 -> 179 | O4: 168 | Q4: =SUM(O4-P4) -> 168 | W4: 168
A5: SABONETE ACÁCIA | B5: 77 | C5: 1 | E5: 117 | F5: =SUM(B5+E5-C5-D5) -> 193 | L5: 1 | M5: =SUM(F5-G5-H5-J5-K5-L5) -> 192 | O5: 188 | Q5: =SUM(O5-P5) -> 188 | S5: 1 | W5: 187
A6: HOME SPRAY AMENDOA | B6: 31 | C6: 1 | D6: 1 | F6: 42 | G6: 1 | J6: 1 | M6: =SUM(F6-G6-H6-J6-K6-L6) -> 40 | O6: =SUM(M6-N6) -> 40 | P6: 2 | Q6: =SUM(O6-P6) -> 38 | W6: 38
A7: HOME SPRAY SANDALO | B7: 28 | C7: 3 | F7: =SUM(B7+E7-C7-D7) -> 25 | M7: =SUM(F7-G7-H7-J7-K7-L7) -> 25 | O7: =SUM(M7-N7) -> 25 | P7: 4 | Q7: =SUM(O7-P7) -> 21 | W7: 21
A8: BODY SPLASH FIGO | B8: 70 | C8: 2 | F8: =SUM(B8+E8-C8-D8) -> 68 | G8: 1 | H8: 1 | K8: 1 | L8: 1 | M8: =SUM(F8-G8-H8-J8-K8-L8) -> 64 | O8: =SUM(M8-N8) -> 64 | P8: 5 | Q8: =SUM(O8-P8) -> 59 | W8: 59
A9: BODY SPLASH ROMÃ | B9: 72 | C9: 8 | F9: =SUM(B9+E9-C9-D9) -> 64 | K9: 1 | M9: =SUM(F9-G9-H9-J9-K9-L9) -> 63 | N9: 1 | O9: =SUM(M9-N9) -> 62 | P9: 5 | Q9: =SUM(O9-P9) -> 57 | W9: 57
A10: REFIL SABONETE NARDO | B10: 0 | C10: 0 | F10: =SUM(B10+E10-C10-D10) -> 0 | K10: 8 | M10: =SUM(F10-G10-H10-J10-K10-L10) -> -8 | O10: 3 | Q10: =SUM(O10-P10) -> 3 | W10: 3
A11: REFIL SABONETE ACÁCIA | B11: 0 | C11: 0 | F11: =SUM(B11+E11-C11-D11) -> 0 | M11: =SUM(F11-G11-H11-J11-K11-L11) -> 0 | O11: 5 | Q11: =SUM(O11-P11) -> 5 | R11: 2 | W11: 3
A12: REFIL DIFUSOR NARDO | B12: 0 | C12: 0 | F12: 10 | M12: =SUM(F12-G12-H12-J12-K12-L12) -> 10 | O12: =SUM(M12-N12) -> 10 | Q12: =SUM(O12-P12) -> 10 | U12: 2 | W12: 10
A13: REFIL DIFUSOR ACÁCIA | B13: 0 | C13: 0 | F13: =SUM(B13+E13-C13-D13) -> 0 | M13: =SUM(F13-G13-H13-J13-K13-L13) -> 0 | N13: 2 | O13: 4 | Q13: =SUM(O13-P13) -> 4 | V13: 1 | W13: 4
A14: VENDA | C14: 1465 | G14: 134.5 | H14: 79 | I14: =SUM(C14:H14) -> 1678.5 | J14: 55.5 | K14: 1187.4 | L14: 359 | N14: =86+86+79+140 -> 391 | P14: 1356 | R14: 170 | S14: 129.9 | T14: =SUM(P14,N14,L14,K14,J14,I14) -> 5027.4 | U14: 172 | V14: 86
B16: Estoque 12/03 | C16: Venda 14/03 | D16: Venda 15/03 | E16: Venda 16/03 | F16: Venda 17/03 | G16: Estoque
A17: DIFUSOR NARDO | B17: 174 | C17: 0 | G17: =SUM(B17-C17-D17-E17-F17) -> 174
A18: DIFUSOR ACACIA | B18: 99 | C18: 1 | G18: =SUM(B18-C18-D18-E18-F18) -> 98
A19: SABONETE NARDO | B19: 168 | C19: 0 | G19: =SUM(B19-C19-D19-E19-F19) -> 168
A20: SABONETE ACÁCIA | B20: 187 | C20: 0 | G20: =SUM(B20-C20-D20-E20-F20) -> 187
A21: HOME SPRAY AMENDOA | B21: 38 | C21: 0 | G21: =SUM(B21-C21-D21-E21-F21) -> 38
A22: HOME SPRAY SANDALO | B22: 21 | C22: 0 | G22: =SUM(B22-C22-D22-E22-F22) -> 21
A23: BODY SPLASH FIGO | B23: 59 | C23: 1 | G23: =SUM(B23-C23-D23-E23-F23) -> 58
A24: BODY SPLASH ROMÃ | B24: 57 | C24: 1 | G24: =SUM(B24-C24-D24-E24-F24) -> 56
A25: REFIL SABONETE NARDO | B25: 3 | C25: 0 | G25: =SUM(B25-C25-D25-E25-F25) -> 3
A26: REFIL SABONETE ACÁCIA | B26: 3 | C26: 1 | G26: =SUM(B26-C26-D26-E26-F26) -> 2
A27: REFIL DIFUSOR NARDO | B27: 10 | C27: 0 | G27: =SUM(B27-C27-D27-E27-F27) -> 10
A28: REFIL DIFUSOR ACÁCIA | B28: 4 | C28: 0 | G28: =SUM(B28-C28-D28-E28-F28) -> 4
A29: VENDA | C29: 403.9
A34: VAREJO | C34: Total 19/02
A35: DIFUSOR NARDO | B35: 159.9 | C35: =SUM(B35*W2) -> 27822.6
A36: DIFUSOR ACACIA | B36: 159.9 | C36: =SUM(B36*W3) -> 15830.1
A37: SABONETE NARDO | B37: 129.9 | C37: =SUM(B37*W4) -> 21823.2
A38: SABONETE ACÁCIA | B38: 129.9 | C38: =SUM(B38*W5) -> 24291.3
A39: HOME SPRAY AMENDOA | B39: 55.5 | C39: =SUM(B39*W6) -> 2109
A40: HOME SPRAY SANDALO | B40: 55.5 | C40: =SUM(B40*W7) -> 1165.5
A41: BODY SPLASH FIGO | B41: 79 | C41: =SUM(B41*W8) -> 4661
A42: BODY SPLASH ROMÃ | B42: 79 | C42: =SUM(B42*W9) -> 4503
A43: REFIL DIFUSOR ACÁCIA | B43: 86 | C43: =SUM(B43*W10) -> 258
A44: REFIL DIFUSOR NARDO | B44: 86 | C44: =SUM(B44*W11) -> 258
A45: REFIL SABONETE ACÁCIA | B45: 46 | C45: =SUM(B45*W12) -> 460
A46: REFIL SABONETE NARDO | B46: 46 | C46: =SUM(B46*W13) -> 184
C47: =SUM(C35:C46) -> 103365.7
A49: ATACADO | C49: Total 19/02
A50: DIFUSOR NARDO | B50: 99.9 | C50: =SUM(B50*W2) -> 17382.6
A51: DIFUSOR ACACIA | B51: 99.9 | C51: =SUM(B51*W3) -> 9890.1
A52: SABONETE NARDO | B52: 69.9 | C52: =SUM(B52*W4) -> 11743.2
A53: SABONETE ACÁCIA | B53: 69.9 | C53: =SUM(B53*W5) -> 13071.3
A54: HOME SPRAY AMENDOA | B54: 34.1 | C54: =SUM(B54*W6) -> 1295.8
A55: HOME SPRAY SANDALO | B55: 34.1 | C55: =SUM(B55*W7) -> 716.1
A56: BODY SPLASH FIGO | B56: 53 | C56: =SUM(B56*W8) -> 3127
A57: BODY SPLASH ROMÃ | B57: 53 | C57: =SUM(B57*W9) -> 3021
A58: REFIL DIFUSOR ACÁCIA | B58: 56.7 | C58: =SUM(B58*W10) -> 170.1
A59: REFIL DIFUSOR NARDO | B59: 56.7 | C59: =SUM(B59*W11) -> 170.1
A60: REFIL SABONETE ACÁCIA | B60: 33.5 | C60: =SUM(B60*W12) -> 335
A61: REFIL SABONETE NARDO | B61: 33.5 | C61: =SUM(B61*W13) -> 134
C62: =SUM(C50:C61) -> 61056.3
A67: PULSEIRA | B67: 37 | C67: 13 | D67: =SUM(C67*B67) -> 481 | E67: =SUM(B67*45) -> 1665
A68: PINGENTE | B68: 299 | C68: 5 | D68: =SUM(B68*C68) -> 1495
D69: =SUM(D67:D68) -> 1976
